extended_ascii
