Metadata-Version: 1.1
Name: extended-ascii
Version: 1.0.1
Summary: Exports anything passed in as ISRI Extended ASCII, a Latin-1 based encoding
Home-page: https://github.com/eddieantonio/isri-extended-ascii
Author: Eddie Antonio Santos
Author-email: easantos@ualberta.ca
License: MIT
Download-URL: https://github.com/eddieantonio/isri-extended-ascii
Platform: UNKNOWN
Classifier: Development Status :: 5 - Production/Stable
Classifier: Programming Language :: Python
Classifier: Programming Language :: Python :: 2
Classifier: Programming Language :: Python :: 2.7
Classifier: Programming Language :: Python :: 3.3
Classifier: Programming Language :: Python :: 3.4
Classifier: Environment :: Console
Classifier: Intended Audience :: Developers
Classifier: License :: OSI Approved :: MIT License
Classifier: Topic :: Software Development
Classifier: Topic :: Text Processing
Classifier: Topic :: Utilities
